code_exec/__init__.py
code_exec/controller/__init__.py
code_exec/controller/api.py
code_exec/main.py
code_exec/model/__init__.py
code_exec/model/model.py
code_exec/serivce/__init__.py
code_exec/serivce/code_dispose.py
code_exec_hz-1.1.0.dist-info/LICENSE.txt
code_exec_hz-1.1.0.dist-info/METADATA
code_exec_hz-1.1.0.dist-info/WHEEL
code_exec_hz-1.1.0.dist-info/entry_points.txt
code_exec_hz-1.1.0.dist-info/RECORD
