Metadata-Version: 2.1
Name: code-exec-hz
Version: 1.1.0
Summary: 
Author: zhushiqi
Author-email: zhushiqi@haizhi.com
Requires-Python: >=3.10,<4.0
Classifier: Programming Language :: Python :: 3
Classifier: Programming Language :: Python :: 3.10
Classifier: Programming Language :: Python :: 3.11
Classifier: Programming Language :: Python :: 3.12
Classifier: Programming Language :: Python :: 3.13
